AUTHORS
CONTRIBUTOR_CONDUCT.md
ChangeLog
LICENSE.txt
README.md
requirements.txt
setup.cfg
setup.py
bookmarkd/__init__.py
bookmarkd/cli.py
bookmarkd/to_notebook.py
bookmarkd/version.py
bookmarkd.egg-info/PKG-INFO
bookmarkd.egg-info/SOURCES.txt
bookmarkd.egg-info/dependency_links.txt
bookmarkd.egg-info/entry_points.txt
bookmarkd.egg-info/not-zip-safe
bookmarkd.egg-info/requires.txt
bookmarkd.egg-info/top_level.txt
samples/simplest.ipynb
samples/simplest.md