Metadata-Version: 1.1
Name: bookmarkd
Version: 0.1
Summary: Convert between IPython notebooks and markdown
Home-page: UNKNOWN
Author: Ryan S. Brown
Author-email: sb@ryansb.com
License: AGPLv3
Keywords: markdown
Platform: UNKNOWN
Classifier: Natural Language :: English
Classifier: Operating System :: POSIX :: Linux
Classifier: Programming Language :: Python :: 2.7
